[
    {
        "title": "On my CV",
        "image": "/images/container_images/gentrack.png",
        "desc": "An article elaborating on my CV",
        "infoText": "Click image to open",
        "artcle_title": "cv",
        "chips": [
            "Article"
        ]
    },
    {
        "title": "example",
        "image": "/images/container_images/gentrack.png",
        "desc": "My new PC build",
        "infoText": "Click image to open",
        "artcle_title": "example",
        "chips": [
            "Article"
        ]
    },
    {
        "title": "Sensor Story App",
        "image": "/images/container_images/sensor_story.png",
        "desc": "A cross platform app created for a client",
        "infoText": "Click image to open",
        "artcle_title": "",
        "chips": [
            "Swift", "Android", "iOS", "Mobile Development", "Freelance", "App Development"
        ]
    },
    {
        "title": "Trip To Italy with Emma",
        "image": "/images/container_images/italy_2023.png",
        "desc": "My december trip to Italy with plenty of photos",
        "infoText": "Click image to open",
        "artcle_title": "",
        "chips": [
            "Photography", "Emma", "Travel"
        ]
    },
    {
        "title": "Globalstep",
        "image": "/images/container_images/globalstep.png",
        "desc": "I am currently employed here",
        "infoText": "Click image to open",
        "artcle_title": "",
        "chips": [
            "Javascript", "Cypress", "QA", "React"
        ]
    },
    {
        "title": "Gentrack",
        "image": "/images/container_images/gentrack.png",
        "desc": "I worked here between 2019 and 2020",
        "infoText": "Click image to open",
        "artcle_title": "",
        "chips": [
            "BASIC", "Full Stack"
        ]
    },
    {
        "title": "Brunel University",
        "image": "/images/container_images/brunel_uni.png",
        "desc": "Obtained a degree in Computer Science",
        "infoText": "Click image to open",
        "artcle_title": "",
        "chips": [
            "Brunel University", "Significant Work", "AI", "Java"
        ]
    },
    {
        "title": "Gamesys",
        "image": "/images/container_images/gamesys.png",
        "desc": "my first job",
        "infoText": "Click image to open",
        "artcle_title": "",
        "chips": [
            "QA", "Writing"
        ]
    },
    {
        "title": "This Website",
        "image": "/images/container_images/gamesys.png",
        "desc": "There've been a few iterations",
        "infoText": "Click image to open",
        "artcle_title": "",
        "chips": [
            "React", "NextJS", "Javascript", "Tailwind"
        ]
    }
]